addsub/__init__.py
addsub/add.py
addsub/subtract.py
addsub/extras/__init__.py
addsub/extras/divide.py
addsub/extras/multiply.py
addsub-0.0.4.dist-info/METADATA
addsub-0.0.4.dist-info/WHEEL
addsub-0.0.4.dist-info/top_level.txt
addsub-0.0.4.dist-info/RECORD
